{
  "annotations": {
    "list": [
      {
        "builtIn": 1,
        "datasource": {
          "type": "grafana",
          "uid": "-- Grafana --"
        },
        "enable": true,
        "hide": true,
        "iconColor": "rgba(0, 211, 255, 1)",
        "name": "Annotations & Alerts",
        "type": "dashboard"
      }
    ]
  },
  "editable": true,
  "fiscalYearStartMonth": 0,
  "graphTooltip": 0,
  "id": 4,
  "links": [],
  "liveNow": false,
  "panels": [
    {
      "datasource": {
        "type": "postgres",
        "uid": "ThreatDetectionDB"
      },
      "fieldConfig": {
        "defaults": {
          "color": {
            "mode": "thresholds"
          },
          "mappings": [],
          "thresholds": {
            "mode": "absolute",
            "steps": [
              {
                "color": "green",
                "value": null
              },
              {
                "color": "red",
                "value": 80
              }
            ]
          },
          "unit": "percent"
        },
        "overrides": []
      },
      "gridPos": {
        "h": 8,
        "w": 6,
        "x": 0,
        "y": 0
      },
      "id": 12,
      "options": {
        "orientation": "auto",
        "reduceOptions": {
          "values": false,
          "calcs": ["lastNotNull"],
          "fields": ""
        },
        "showThresholdLabels": false,
        "showThresholdMarkers": true
      },
      "pluginVersion": "10.0.0",
      "targets": [
        {
          "datasource": {
            "type": "postgres",
            "uid": "ThreatDetectionDB"
          },
          "format": "table",
          "group": [],
          "metricColumn": "none",
          "rawQuery": true,
          "rawSql": "SELECT \n  cpu_usage as \"CPU Usage\"\nFROM system_info \nORDER BY timestamp DESC\nLIMIT 1",
          "refId": "A",
          "select": [
            [
              {
                "params": ["*"],
                "type": "column"
              }
            ]
          ],
          "table": "system_info",
          "timeColumn": "timestamp",
          "timeColumnType": "timestamp",
          "where": [
            {
              "name": "$__timeFilter",
              "params": [],
              "type": "macro"
            }
          ]
        }
      ],
      "title": "Current CPU Usage",
      "type": "gauge"
    },
    {
      "datasource": {
        "type": "postgres",
        "uid": "ThreatDetectionDB"
      },
      "fieldConfig": {
        "defaults": {
          "color": {
            "mode": "thresholds"
          },
          "mappings": [],
          "thresholds": {
            "mode": "absolute",
            "steps": [
              {
                "color": "green",
                "value": null
              },
              {
                "color": "yellow",
                "value": 70
              },
              {
                "color": "red",
                "value": 90
              }
            ]
          },
          "unit": "percent"
        },
        "overrides": []
      },
      "gridPos": {
        "h": 8,
        "w": 6,
        "x": 6,
        "y": 0
      },
      "id": 13,
      "options": {
        "orientation": "auto",
        "reduceOptions": {
          "values": false,
          "calcs": ["lastNotNull"],
          "fields": ""
        },
        "showThresholdLabels": false,
        "showThresholdMarkers": true
      },
      "pluginVersion": "10.0.0",
      "targets": [
        {
          "datasource": {
            "type": "postgres",
            "uid": "ThreatDetectionDB"
          },
          "format": "table",
          "group": [],
          "metricColumn": "none",
          "rawQuery": true,
          "rawSql": "SELECT \n  ((total_memory - available_memory)::float / total_memory::float) * 100 as \"Memory Usage\"\nFROM system_info \nORDER BY timestamp DESC\nLIMIT 1",
          "refId": "A",
          "select": [
            [
              {
                "params": ["*"],
                "type": "column"
              }
            ]
          ],
          "table": "system_info",
          "timeColumn": "timestamp",
          "timeColumnType": "timestamp",
          "where": [
            {
              "name": "$__timeFilter",
              "params": [],
              "type": "macro"
            }
          ]
        }
      ],
      "title": "Current Memory Usage",
      "type": "gauge"
    },
    {
      "datasource": {
        "type": "postgres",
        "uid": "ThreatDetectionDB"
      },
      "fieldConfig": {
        "defaults": {
          "color": {
            "mode": "thresholds"
          },
          "mappings": [],
          "thresholds": {
            "mode": "absolute",
            "steps": [
              {
                "color": "green",
                "value": null
              },
              {
                "color": "yellow",
                "value": 80
              },
              {
                "color": "red",
                "value": 95
              }
            ]
          },
          "unit": "percent"
        },
        "overrides": []
      },
      "gridPos": {
        "h": 8,
        "w": 6,
        "x": 12,
        "y": 0
      },
      "id": 14,
      "options": {
        "orientation": "auto",
        "reduceOptions": {
          "values": false,
          "calcs": ["lastNotNull"],
          "fields": ""
        },
        "showThresholdLabels": false,
        "showThresholdMarkers": true
      },
      "pluginVersion": "10.0.0",
      "targets": [
        {
          "datasource": {
            "type": "postgres",
            "uid": "ThreatDetectionDB"
          },
          "format": "table",
          "group": [],
          "metricColumn": "none",
          "rawQuery": true,
          "rawSql": "SELECT \n  disk_usage as \"Disk Usage\"\nFROM system_info \nORDER BY timestamp DESC\nLIMIT 1",
          "refId": "A",
          "select": [
            [
              {
                "params": ["*"],
                "type": "column"
              }
            ]
          ],
          "table": "system_info",
          "timeColumn": "timestamp",
          "timeColumnType": "timestamp",
          "where": [
            {
              "name": "$__timeFilter",
              "params": [],
              "type": "macro"
            }
          ]
        }
      ],
      "title": "Current Disk Usage",
      "type": "gauge"
    },
    {
      "datasource": {
        "type": "postgres",
        "uid": "ThreatDetectionDB"
      },
      "fieldConfig": {
        "defaults": {
          "color": {
            "mode": "palette-classic"
          },
          "mappings": [],
          "thresholds": {
            "mode": "absolute",
            "steps": [
              {
                "color": "green",
                "value": null
              },
              {
                "color": "red",
                "value": 80
              }
            ]
          },
          "unit": "s"
        },
        "overrides": []
      },
      "gridPos": {
        "h": 8,
        "w": 6,
        "x": 18,
        "y": 0
      },
      "id": 15,
      "options": {
        "colorMode": "value",
        "graphMode": "area",
        "justifyMode": "auto",
        "orientation": "auto",
        "reduceOptions": {
          "values": false,
          "calcs": ["lastNotNull"],
          "fields": ""
        },
        "textMode": "auto"
      },
      "pluginVersion": "10.0.0",
      "targets": [
        {
          "datasource": {
            "type": "postgres",
            "uid": "ThreatDetectionDB"
          },
          "format": "table",
          "group": [],
          "metricColumn": "none",
          "rawQuery": true,
          "rawSql": "SELECT \n  uptime as \"System Uptime\"\nFROM system_info \nORDER BY timestamp DESC\nLIMIT 1",
          "refId": "A",
          "select": [
            [
              {
                "params": ["*"],
                "type": "column"
              }
            ]
          ],
          "table": "system_info",
          "timeColumn": "timestamp",
          "timeColumnType": "timestamp",
          "where": [
            {
              "name": "$__timeFilter",
              "params": [],
              "type": "macro"
            }
          ]
        }
      ],
      "title": "System Uptime",
      "type": "stat"
    },
    {
      "datasource": {
        "type": "postgres",
        "uid": "ThreatDetectionDB"
      },
      "fieldConfig": {
        "defaults": {
          "color": {
            "mode": "palette-classic"
          },
          "custom": {
            "axisLabel": "",
            "axisPlacement": "auto",
            "barAlignment": 0,
            "drawStyle": "line",
            "fillOpacity": 10,
            "gradientMode": "none",
            "hideFrom": {
              "legend": false,
              "tooltip": false,
              "vis": false
            },
            "lineInterpolation": "linear",
            "lineWidth": 1,
            "pointSize": 5,
            "scaleDistribution": {
              "type": "linear"
            },
            "showPoints": "auto",
            "spanNulls": false,
            "stacking": {
              "group": "A",
              "mode": "none"
            },
            "thresholdsStyle": {
              "mode": "off"
            }
          },
          "mappings": [],
          "thresholds": {
            "mode": "absolute",
            "steps": [
              {
                "color": "green",
                "value": null
              },
              {
                "color": "red",
                "value": 80
              }
            ]
          },
          "unit": "percent"
        },
        "overrides": []
      },
      "gridPos": {
        "h": 8,
        "w": 12,
        "x": 0,
        "y": 8
      },
      "id": 16,
      "options": {
        "legend": {
          "calcs": [],
          "displayMode": "list",
          "placement": "bottom",
          "showLegend": true
        },
        "tooltip": {
          "mode": "single",
          "sort": "none"
        }
      },
      "targets": [
        {
          "datasource": {
            "type": "postgres",
            "uid": "ThreatDetectionDB"
          },
          "format": "time_series",
          "group": [],
          "metricColumn": "none",
          "rawQuery": true,
          "rawSql": "SELECT \n  timestamp as time,\n  cpu_usage as \"CPU Usage %\"\nFROM system_info \nWHERE $__timeFilter(timestamp)\nORDER BY timestamp",
          "refId": "A",
          "select": [
            [
              {
                "params": ["*"],
                "type": "column"
              }
            ]
          ],
          "table": "system_info",
          "timeColumn": "timestamp",
          "timeColumnType": "timestamp",
          "where": [
            {
              "name": "$__timeFilter",
              "params": [],
              "type": "macro"
            }
          ]
        }
      ],
      "title": "CPU Usage Over Time",
      "type": "timeseries"
    },
    {
      "datasource": {
        "type": "postgres",
        "uid": "ThreatDetectionDB"
      },
      "fieldConfig": {
        "defaults": {
          "color": {
            "mode": "palette-classic"
          },
          "custom": {
            "axisLabel": "",
            "axisPlacement": "auto",
            "barAlignment": 0,
            "drawStyle": "line",
            "fillOpacity": 10,
            "gradientMode": "none",
            "hideFrom": {
              "legend": false,
              "tooltip": false,
              "vis": false
            },
            "lineInterpolation": "linear",
            "lineWidth": 1,
            "pointSize": 5,
            "scaleDistribution": {
              "type": "linear"
            },
            "showPoints": "auto",
            "spanNulls": false,
            "stacking": {
              "group": "A",
              "mode": "none"
            },
            "thresholdsStyle": {
              "mode": "off"
            }
          },
          "mappings": [],
          "thresholds": {
            "mode": "absolute",
            "steps": [
              {
                "color": "green",
                "value": null
              },
              {
                "color": "red",
                "value": 80
              }
            ]
          },
          "unit": "bytes"
        },
        "overrides": []
      },
      "gridPos": {
        "h": 8,
        "w": 12,
        "x": 12,
        "y": 8
      },
      "id": 17,
      "options": {
        "legend": {
          "calcs": [],
          "displayMode": "list",
          "placement": "bottom",
          "showLegend": true
        },
        "tooltip": {
          "mode": "multi",
          "sort": "none"
        }
      },
      "targets": [
        {
          "datasource": {
            "type": "postgres",
            "uid": "ThreatDetectionDB"
          },
          "format": "time_series",
          "group": [],
          "metricColumn": "none",
          "rawQuery": true,
          "rawSql": "SELECT \n  timestamp as time,\n  total_memory as \"Total Memory\",\n  available_memory as \"Available Memory\",\n  (total_memory - available_memory) as \"Used Memory\"\nFROM system_info \nWHERE $__timeFilter(timestamp)\nORDER BY timestamp",
          "refId": "A",
          "select": [
            [
              {
                "params": ["*"],
                "type": "column"
              }
            ]
          ],
          "table": "system_info",
          "timeColumn": "timestamp",
          "timeColumnType": "timestamp",
          "where": [
            {
              "name": "$__timeFilter",
              "params": [],
              "type": "macro"
            }
          ]
        }
      ],
      "title": "Memory Usage Over Time",
      "type": "timeseries"
    },
    {
      "datasource": {
        "type": "postgres",
        "uid": "ThreatDetectionDB"
      },
      "fieldConfig": {
        "defaults": {
          "color": {
            "mode": "thresholds"
          },
          "custom": {
            "align": "auto",
            "cellOptions": {
              "type": "auto"
            },
            "inspect": false
          },
          "mappings": [],
          "thresholds": {
            "mode": "absolute",
            "steps": [
              {
                "color": "green",
                "value": null
              },
              {
                "color": "red",
                "value": 80
              }
            ]
          }
        },
        "overrides": [
          {
            "matcher": {
              "id": "byName",
              "options": "Total Memory"
            },
            "properties": [
              {
                "id": "unit",
                "value": "bytes"
              }
            ]
          },
          {
            "matcher": {
              "id": "byName",
              "options": "Available Memory"
            },
            "properties": [
              {
                "id": "unit",
                "value": "bytes"
              }
            ]
          },
          {
            "matcher": {
              "id": "byName",
              "options": "CPU Usage"
            },
            "properties": [
              {
                "id": "unit",
                "value": "percent"
              }
            ]
          },
          {
            "matcher": {
              "id": "byName",
              "options": "Disk Usage"
            },
            "properties": [
              {
                "id": "unit",
                "value": "percent"
              }
            ]
          },
          {
            "matcher": {
              "id": "byName",
              "options": "Uptime"
            },
            "properties": [
              {
                "id": "unit",
                "value": "s"
              }
            ]
          }
        ]
      },
      "gridPos": {
        "h": 8,
        "w": 24,
        "x": 0,
        "y": 16
      },
      "id": 18,
      "options": {
        "cellHeight": "sm",
        "footer": {
          "countRows": false,
          "fields": "",
          "reducer": ["sum"],
          "show": false
        },
        "showHeader": true,
        "sortBy": [
          {
            "desc": true,
            "displayName": "Timestamp"
          }
        ]
      },
      "pluginVersion": "10.0.0",
      "targets": [
        {
          "datasource": {
            "type": "postgres",
            "uid": "ThreatDetectionDB"
          },
          "format": "table",
          "group": [],
          "metricColumn": "none",
          "rawQuery": true,
          "rawSql": "SELECT \n  timestamp as \"Timestamp\",\n  hostname as \"Hostname\",\n  os_version as \"OS Version\",\n  architecture as \"Architecture\",\n  total_memory as \"Total Memory\",\n  available_memory as \"Available Memory\",\n  cpu_count as \"CPU Count\",\n  cpu_usage as \"CPU Usage\",\n  disk_usage as \"Disk Usage\",\n  uptime as \"Uptime\"\nFROM system_info \nORDER BY timestamp DESC\nLIMIT 20",
          "refId": "A",
          "select": [
            [
              {
                "params": ["*"],
                "type": "column"
              }
            ]
          ],
          "table": "system_info",
          "timeColumn": "timestamp",
          "timeColumnType": "timestamp",
          "where": [
            {
              "name": "$__timeFilter",
              "params": [],
              "type": "macro"
            }
          ]
        }
      ],
      "title": "System Information History",
      "type": "table"
    }
  ],
  "refresh": "30s",
  "schemaVersion": 38,
  "style": "dark",
  "tags": [
    "threat-detection",
    "system"
  ],
  "templating": {
    "list": []
  },
  "time": {
    "from": "now-6h",
    "to": "now"
  },
  "timepicker": {},
  "timezone": "",
  "title": "System Performance Dashboard",
  "uid": "system-performance",
  "version": 1,
  "weekStart": ""
}